Metadata-Version: 2.1
Name: breath-detector
Version: 0.3
Summary: breath detector in Lingjing Env
Author: jasine
Author-email: jasinechen@gmail.com
Requires-Dist: scipy
Requires-Dist: numpy
